treelab/__init__.py
treelab/api.py
treelab/client.py
treelab/config.py
treelab/consts.py
treelab/helper.py
treelab/pysdk.ini
treelab/wrapper_classes.py
treelab/event_handling/__init__.py
treelab/event_handling/event_handler.py
treelab/event_handling/listenable.py
treelab/event_handling/listener.py
treelab/grpc_treelab/__init__.py
treelab/grpc_treelab/messages/__init__.py
treelab/grpc_treelab/messages/service_pb2.py
treelab/grpc_treelab/messages/service_pb2_grpc.py
treelab/utils/__init__.py
treelab/utils/decorator_utils.py
treelab/utils/misc_utils.py
treelab/utils/sleep_cycle_utils.py
treelab-1.6.0.dist-info/METADATA
treelab-1.6.0.dist-info/WHEEL
treelab-1.6.0.dist-info/top_level.txt
treelab-1.6.0.dist-info/zip-safe
treelab-1.6.0.dist-info/RECORD
