Metadata-Version: 2.1
Name: treelab
Version: 1.6.0
Summary: UNKNOWN
Home-page: https://caminerinc.github.io/treelab-pySDK/
License: BSD License
Platform: UNKNOWN
Requires-Python: >=3
Requires-Dist: Rx (>=3.0.0a3)
Requires-Dist: grpcio (>=1.22.0)
Requires-Dist: grpcio-tools (>=1.22.0)
Requires-Dist: pandas (>=0.24.2)
Requires-Dist: filestack-python (>=3.0.1)
